weather_reporter/cli.py
weather_reporter/utils.py
weather_reporter_kishor-1.0.0.dist-info/LICENSE
weather_reporter_kishor-1.0.0.dist-info/METADATA
weather_reporter_kishor-1.0.0.dist-info/WHEEL
weather_reporter_kishor-1.0.0.dist-info/entry_points.txt
weather_reporter_kishor-1.0.0.dist-info/top_level.txt
weather_reporter_kishor-1.0.0.dist-info/RECORD
